test_history_server/VERSION
test_history_server/__init__.py
test_history_server/manage.py
test_history_server/cli/__init__.py
test_history_server/cli/__main__.py
test_history_server/cli/apps.py
test_history_server/core/__init__.py
test_history_server/core/apps.py
test_history_server/core/models.py
test_history_server/html/__init__.py
test_history_server/html/apps.py
test_history_server/html/urls.py
test_history_server/html/views.py
test_history_server/rest/__init__.py
test_history_server/rest/apps.py
test_history_server/rest/forms.py
test_history_server/rest/urls.py
test_history_server/rest/views.py
test_history_server/site/__init__.py
test_history_server/site/settings.py
test_history_server/site/urls.py
test_history_server/site/wsgi.py
test_history_server-0.0.3.dist-info/METADATA
test_history_server-0.0.3.dist-info/RECORD
test_history_server-0.0.3.dist-info/WHEEL
test_history_server-0.0.3.dist-info/dependency_links.txt
test_history_server-0.0.3.dist-info/top_level.txt
